{"sic_code":"8090","sic_industry":"Services-Health Services","sic_major_group":"Services","period":"6m","start_date":"2025-11-16","end_date":"2026-05-14","total_buy_usd":652232.0,"num_companies":2,"items":[{"ticker":"PARK","company_name":"Park Dental Partners, Inc.","cik":"0002069604","market_cap_usd":82264280.77975845,"buy_value_usd":351182.0,"ratio_to_mcap":0.004268948766964849,"num_insiders":6,"num_buy_days":1,"last_buy_date":"2025-12-03"},{"ticker":"AGL","company_name":"agilon health, inc.","cik":"0001831097","market_cap_usd":1201399465.500412,"buy_value_usd":301050.0,"ratio_to_mcap":0.00025058276505442374,"num_insiders":3,"num_buy_days":2,"last_buy_date":"2026-03-09"}]}