{"sic_code":"6036","sic_industry":"Savings Institutions, State-Chartered","sic_major_group":"Finance, Insurance, Real Estate","period":"6m","start_date":"2025-11-14","end_date":"2026-05-12","total_buy_usd":5578664.4678,"num_companies":15,"items":[{"ticker":"HYNE","company_name":"Hoyne Bancorp, Inc.","cik":"0002073153","market_cap_usd":116986083.67876911,"buy_value_usd":2428915.6,"ratio_to_mcap":0.020762431937370728,"num_insiders":10,"num_buy_days":3,"last_buy_date":"2025-12-05"},{"ticker":"AVBC","company_name":"Avidia Bancorp, Inc.","cik":"0002058758","market_cap_usd":360064328.7194252,"buy_value_usd":933336.5174,"ratio_to_mcap":0.002592138245739107,"num_insiders":9,"num_buy_days":15,"last_buy_date":"2026-05-08"},{"ticker":"NBBK","company_name":"NB Bancorp, Inc.","cik":"0001979330","market_cap_usd":878740406.5715675,"buy_value_usd":758201.6799999999,"ratio_to_mcap":0.0008628278321218286,"num_insiders":4,"num_buy_days":5,"last_buy_date":"2026-04-24"},{"ticker":"GCBC","company_name":"GREENE COUNTY BANCORP INC","cik":"0001070524","market_cap_usd":405238493.40956116,"buy_value_usd":462579.9,"ratio_to_mcap":0.0011415003942690256,"num_insiders":6,"num_buy_days":8,"last_buy_date":"2026-04-28"},{"ticker":"HFWA","company_name":"HERITAGE FINANCIAL CORP /WA/","cik":"0001046025","market_cap_usd":1131071520.8071156,"buy_value_usd":426445.92,"ratio_to_mcap":0.0003770282534350212,"num_insiders":1,"num_buy_days":1,"last_buy_date":"2025-11-20"},{"ticker":"SRBK","company_name":"SR Bancorp, Inc.","cik":"0001951276","market_cap_usd":136476175.30302048,"buy_value_usd":153794.98039999997,"ratio_to_mcap":0.001126899842104501,"num_insiders":7,"num_buy_days":10,"last_buy_date":"2026-03-16"},{"ticker":"WSBK","company_name":"Winchester Bancorp, Inc./MD/","cik":"0002047235","market_cap_usd":114697512.10912609,"buy_value_usd":133019.2,"ratio_to_mcap":0.00115973919184439,"num_insiders":2,"num_buy_days":3,"last_buy_date":"2026-05-07"},{"ticker":"ECBK","company_name":"ECB Bancorp, Inc. /MD/","cik":"0001914605","market_cap_usd":161950033.46805573,"buy_value_usd":100392.20000000001,"ratio_to_mcap":0.0006198961361733967,"num_insiders":2,"num_buy_days":4,"last_buy_date":"2026-04-30"},{"ticker":"TCBX","company_name":"Third Coast Bancshares, Inc.","cik":"0001781730","market_cap_usd":616063613.9522438,"buy_value_usd":52462.8,"ratio_to_mcap":8.515808889188322e-05,"num_insiders":2,"num_buy_days":2,"last_buy_date":"2026-02-24"},{"ticker":"FNWB","company_name":"First Northwest Bancorp","cik":"0001556727","market_cap_usd":86294097.77348614,"buy_value_usd":49655.7,"ratio_to_mcap":0.0005754240589007782,"num_insiders":1,"num_buy_days":1,"last_buy_date":"2026-02-06"},{"ticker":"BSBK","company_name":"Bogota Financial Corp.","cik":"0001787414","market_cap_usd":106158851.70376396,"buy_value_usd":31394.000000000004,"ratio_to_mcap":0.00029572663509591163,"num_insiders":1,"num_buy_days":3,"last_buy_date":"2025-12-12"},{"ticker":"HBCP","company_name":"HOME BANCORP, INC.","cik":"0001436425","market_cap_usd":502634192.0694275,"buy_value_usd":29750.0,"ratio_to_mcap":5.918817396308509e-05,"num_insiders":1,"num_buy_days":1,"last_buy_date":"2026-02-19"},{"ticker":"MBBC","company_name":"Marathon Bancorp, Inc. /MD/","cik":"0001835385","market_cap_usd":43573510.07046509,"buy_value_usd":12222.75,"ratio_to_mcap":0.000280508730653875,"num_insiders":1,"num_buy_days":1,"last_buy_date":"2025-11-26"},{"ticker":"FBLA","company_name":"FB Bancorp, Inc. /MD/","cik":"0002013639","market_cap_usd":190236008.45036888,"buy_value_usd":5272.469999999999,"ratio_to_mcap":2.7715415409252273e-05,"num_insiders":2,"num_buy_days":3,"last_buy_date":"2026-02-23"},{"ticker":"FLG","company_name":"FLAGSTAR BANK, NATIONAL ASSOCIATION","cik":"0000910073","market_cap_usd":5834883502.0,"buy_value_usd":1220.75,"ratio_to_mcap":2.09215830887038e-07,"num_insiders":1,"num_buy_days":1,"last_buy_date":"2025-12-04"}]}