{"sic_code":"7373","sic_industry":"Services-Computer Integrated Systems Design","sic_major_group":"Services","period":"1w","start_date":"2026-05-14","end_date":"2026-05-20","total_buy_usd":340530.0,"num_companies":2,"items":[{"ticker":"JKHY","company_name":"JACK HENRY & ASSOCIATES INC","cik":"0000779152","market_cap_usd":9982634590.0,"buy_value_usd":317135.0,"ratio_to_mcap":3.176866759379199e-05,"num_insiders":2,"num_buy_days":1,"last_buy_date":"2026-05-14"},{"ticker":"CSPI","company_name":"CSP INC /MA/","cik":"0000356037","market_cap_usd":95178952.22894764,"buy_value_usd":23395.0,"ratio_to_mcap":0.00024580014228066556,"num_insiders":1,"num_buy_days":1,"last_buy_date":"2026-05-15"}]}