{"sic_code":"3751","sic_industry":"Motorcycles, Bicycles & Parts","sic_major_group":"Manufacturing","period":"1y","start_date":"2025-04-27","end_date":"2026-04-26","total_buy_usd":774072.48,"num_companies":2,"items":[{"ticker":"HOG","company_name":"HARLEY-DAVIDSON, INC.","cik":"0000793952","market_cap_usd":2569207355.3083134,"buy_value_usd":461751.68,"ratio_to_mcap":0.00017972534565805347,"num_insiders":3,"num_buy_days":3,"last_buy_date":"2026-03-09"},{"ticker":"FOXF","company_name":"FOX FACTORY HOLDING CORP","cik":"0001424929","market_cap_usd":719143971.1039848,"buy_value_usd":312320.8,"ratio_to_mcap":0.000434295235098119,"num_insiders":1,"num_buy_days":1,"last_buy_date":"2025-11-14"}]}