{"sic_code":"1311","sic_industry":"Crude Petroleum & Natural Gas","sic_major_group":"Mining","period":"1w","start_date":"2026-05-15","end_date":"2026-05-21","total_buy_usd":4596907.507300001,"num_companies":4,"items":[{"ticker":"TXO","company_name":"TXO Partners, L.P.","cik":"0001559432","market_cap_usd":730858342.3219872,"buy_value_usd":3933380.7573,"ratio_to_mcap":0.0053818647602808765,"num_insiders":1,"num_buy_days":3,"last_buy_date":"2026-05-20"},{"ticker":"GRNT","company_name":"Granite Ridge Resources, Inc.","cik":"0001928446","market_cap_usd":745212356.0785818,"buy_value_usd":566430.0,"ratio_to_mcap":0.0007600920668849868,"num_insiders":2,"num_buy_days":2,"last_buy_date":"2026-05-19"},{"ticker":"PROP","company_name":"Prairie Operating Co.","cik":"0001162896","market_cap_usd":81508631.44315803,"buy_value_usd":79858.25,"ratio_to_mcap":0.0009797520653464908,"num_insiders":2,"num_buy_days":1,"last_buy_date":"2026-05-19"},{"ticker":"AGIG","company_name":"ABUNDIA GLOBAL IMPACT GROUP, INC.","cik":"0001156041","market_cap_usd":51506698.68074548,"buy_value_usd":17238.5,"ratio_to_mcap":0.00033468462241871837,"num_insiders":1,"num_buy_days":1,"last_buy_date":"2026-05-18"}]}