{"sic_code":"6531","sic_industry":"Real Estate Agents & Managers (For Others)","sic_major_group":"Finance, Insurance, Real Estate","period":"1y","start_date":"2025-04-27","end_date":"2026-04-26","total_buy_usd":64593672.8479,"num_companies":4,"items":[{"ticker":"VAC","company_name":"MARRIOTT VACATIONS WORLDWIDE Corp","cik":"0001524358","market_cap_usd":2482782993.116432,"buy_value_usd":58156600.495900005,"ratio_to_mcap":0.02342395636555446,"num_insiders":11,"num_buy_days":12,"last_buy_date":"2026-03-10"},{"ticker":"OPEN","company_name":"Opendoor Technologies Inc.","cik":"0001801169","market_cap_usd":5165374214.639744,"buy_value_usd":6132897.85,"ratio_to_mcap":0.0011873094949477413,"num_insiders":3,"num_buy_days":4,"last_buy_date":"2025-11-11"},{"ticker":"DOUG","company_name":"Douglas Elliman Inc.","cik":"0001878897","market_cap_usd":166730964.11803937,"buy_value_usd":253682.42719999998,"ratio_to_mcap":0.0015215075888387606,"num_insiders":1,"num_buy_days":3,"last_buy_date":"2025-05-12"},{"ticker":"MMI","company_name":"Marcus & Millichap, Inc.","cik":"0001578732","market_cap_usd":1080016739.218752,"buy_value_usd":50492.074799999995,"ratio_to_mcap":4.6751196501384114e-05,"num_insiders":1,"num_buy_days":1,"last_buy_date":"2025-08-11"}]}