{"sic_code":"6798","sic_industry":"Real Estate Investment Trusts","sic_major_group":"Finance, Insurance, Real Estate","period":"1w","start_date":"2026-05-13","end_date":"2026-05-19","total_buy_usd":6654595.976000001,"num_companies":6,"items":[{"ticker":"AAT","company_name":"American Assets Trust, Inc.","cik":"0001500217","market_cap_usd":1292893079.373703,"buy_value_usd":5387162.4,"ratio_to_mcap":0.004166750124928833,"num_insiders":1,"num_buy_days":4,"last_buy_date":"2026-05-18"},{"ticker":"ADC","company_name":"AGREE REALTY CORP","cik":"0000917251","market_cap_usd":9100193223.252678,"buy_value_usd":1058893.45,"ratio_to_mcap":0.00011635944688452671,"num_insiders":2,"num_buy_days":1,"last_buy_date":"2026-05-14"},{"ticker":"AMH","company_name":"American Homes 4 Rent","cik":"0001562401","market_cap_usd":11499393208.789917,"buy_value_usd":116883.16,"ratio_to_mcap":1.0164289356646814e-05,"num_insiders":1,"num_buy_days":3,"last_buy_date":"2026-05-18"},{"ticker":"XRN","company_name":"Chiron Real Estate Inc.","cik":"0001533615","market_cap_usd":451440059.37789917,"buy_value_usd":49873.666000000005,"ratio_to_mcap":0.00011047682846030042,"num_insiders":1,"num_buy_days":1,"last_buy_date":"2026-05-14"},{"ticker":"SELF","company_name":"Global Self Storage, Inc.","cik":"0001031235","market_cap_usd":60535181.77852249,"buy_value_usd":21320.0,"ratio_to_mcap":0.0003521918886442364,"num_insiders":1,"num_buy_days":1,"last_buy_date":"2026-05-14"},{"ticker":"ABR","company_name":"ARBOR REALTY TRUST INC","cik":"0001253986","market_cap_usd":1161861658.7820024,"buy_value_usd":20463.3,"ratio_to_mcap":1.7612509927775732e-05,"num_insiders":1,"num_buy_days":1,"last_buy_date":"2026-05-14"}]}