{"sic_code":"2650","sic_industry":"Paperboard Containers & Boxes","sic_major_group":"Manufacturing","period":"6m","start_date":"2025-11-21","end_date":"2026-05-19","total_buy_usd":1794466.86807936,"num_companies":2,"items":[{"ticker":"GPK","company_name":"GRAPHIC PACKAGING HOLDING CO","cik":"0001408075","market_cap_usd":3021010232.557208,"buy_value_usd":1054285.3342776,"ratio_to_mcap":0.00034898436387789867,"num_insiders":4,"num_buy_days":3,"last_buy_date":"2026-05-08"},{"ticker":"SON","company_name":"SONOCO PRODUCTS CO","cik":"0000091767","market_cap_usd":4949366707.115482,"buy_value_usd":740181.53380176,"ratio_to_mcap":0.0001495507562083921,"num_insiders":2,"num_buy_days":2,"last_buy_date":"2026-04-27"}]}