{"sic_code":"5810","sic_industry":"Retail-Eating & Drinking Places","sic_major_group":"Retail Trade","period":"1y","start_date":"2025-05-21","end_date":"2026-05-20","total_buy_usd":77432081.7928,"num_companies":5,"items":[{"ticker":"BRCB","company_name":"Black Rock Coffee Bar, Inc.","cik":"0002068577","market_cap_usd":144106921.53676748,"buy_value_usd":72988509.19999999,"ratio_to_mcap":0.5064885740507452,"num_insiders":1,"num_buy_days":1,"last_buy_date":"2026-05-15"},{"ticker":"SHAK","company_name":"Shake Shack Inc.","cik":"0001620533","market_cap_usd":2587289046.6665955,"buy_value_usd":3232567.5928,"ratio_to_mcap":0.0012494033463191006,"num_insiders":6,"num_buy_days":1,"last_buy_date":"2026-05-15"},{"ticker":"SBUX","company_name":"STARBUCKS CORP","cik":"0000829224","market_cap_usd":120511875565.33813,"buy_value_usd":994500.0,"ratio_to_mcap":8.252298749269819e-06,"num_insiders":1,"num_buy_days":1,"last_buy_date":"2025-11-10"},{"ticker":"WEN","company_name":"Wendy's Co","cik":"0000030697","market_cap_usd":1314217115.5642767,"buy_value_usd":114155.0,"ratio_to_mcap":8.686159893069572e-05,"num_insiders":5,"num_buy_days":5,"last_buy_date":"2025-11-20"},{"ticker":"BROS","company_name":"Dutch Bros Inc.","cik":"0001866581","market_cap_usd":7239654725.741798,"buy_value_usd":102350.0,"ratio_to_mcap":1.4137414542171123e-05,"num_insiders":1,"num_buy_days":1,"last_buy_date":"2026-05-15"}]}