{"date":"2026-04-30","total_buys":12,"total_value_usd":12669176.98968,"items":[{"rank":1,"ticker":"SPMA","company_name":"Sound Point Meridian Capital, Inc.","cik":"0001930147","sic_code":null,"sic_industry":null,"sic_major_group":null,"buy_value_usd":12000000.019679999,"market_cap_usd":0,"ratio_to_mcap":0,"num_insiders":1,"top_insider":{"name":"ASSURED GUARANTY LTD","title":null},"transactions":[{"date":"2026-04-30","insider_name":"ASSURED GUARANTY LTD","insider_title":null,"shares":242718.447,"price":24.72,"value_usd":6000000.0098399995},{"date":"2026-04-30","insider_name":"ASSURED GUARANTY LTD","insider_title":null,"shares":242718.447,"price":24.72,"value_usd":6000000.0098399995}]},{"rank":2,"ticker":"GEHC","company_name":"GE HealthCare Technologies Inc.","cik":"0001932393","sic_code":"3844","sic_industry":"X-Ray Apparatus & Tubes & Related Irradiation Apparatus","sic_major_group":"Manufacturing","buy_value_usd":355614.82499999995,"market_cap_usd":27675616329.650978,"ratio_to_mcap":1.2849391347393516e-05,"num_insiders":2,"top_insider":{"name":"Arduini Peter J","title":"President and CEO"},"transactions":[{"date":"2026-04-30","insider_name":"Arduini Peter J","insider_title":"President and CEO","shares":4169.0,"price":59.925,"value_usd":249827.32499999998},{"date":"2026-04-30","insider_name":"Jimenez Frank R","insider_title":"GC & Corporate Secretary","shares":1750.0,"price":60.45,"value_usd":105787.5}]},{"rank":3,"ticker":"ANIK","company_name":"Anika Therapeutics, Inc.","cik":"0000898437","sic_code":"3841","sic_industry":"Surgical & Medical Instruments & Apparatus","sic_major_group":"Manufacturing","buy_value_usd":149880.66,"market_cap_usd":165655016.26215363,"ratio_to_mcap":0.0009047758611958344,"num_insiders":1,"top_insider":{"name":"Griffin Stephen D.","title":"President and CEO"},"transactions":[{"date":"2026-04-30","insider_name":"Griffin Stephen D.","insider_title":"President and CEO","shares":12200.0,"price":12.2853,"value_usd":149880.66}]},{"rank":4,"ticker":"GOF","company_name":"GUGGENHEIM STRATEGIC OPPORTUNITIES FUND","cik":"0001380936","sic_code":null,"sic_industry":null,"sic_major_group":null,"buy_value_usd":99729.5,"market_cap_usd":2423652926.310425,"ratio_to_mcap":4.114842472590339e-05,"num_insiders":1,"top_insider":{"name":"LYDON THOMAS F JR","title":null},"transactions":[{"date":"2026-04-30","insider_name":"LYDON THOMAS F JR","insider_title":null,"shares":8710.0,"price":11.45,"value_usd":99729.5}]},{"rank":5,"ticker":"NWFL","company_name":"NORWOOD FINANCIAL CORP","cik":"0001013272","sic_code":"6022","sic_industry":"State Commercial Banks","sic_major_group":"Finance, Insurance, Real Estate","buy_value_usd":29440.0,"market_cap_usd":318755163.8051224,"ratio_to_mcap":9.235928807728668e-05,"num_insiders":1,"top_insider":{"name":"McCaffery John Martin JR","title":"EVP & CFO"},"transactions":[{"date":"2026-04-30","insider_name":"McCaffery John Martin JR","insider_title":"EVP & CFO","shares":1000.0,"price":29.44,"value_usd":29440.0}]},{"rank":6,"ticker":"MRBK","company_name":"Meridian Corp","cik":"0001750735","sic_code":"6021","sic_industry":"National Commercial Banks","sic_major_group":"Finance, Insurance, Real Estate","buy_value_usd":18415.0,"market_cap_usd":223566126.33476257,"ratio_to_mcap":8.236936561859026e-05,"num_insiders":1,"top_insider":{"name":"Warriner Kenneth Thomas","title":null},"transactions":[{"date":"2026-04-30","insider_name":"Warriner Kenneth Thomas","insider_title":null,"shares":1000.0,"price":18.415,"value_usd":18415.0}]},{"rank":7,"ticker":"AUBN","company_name":"AUBURN NATIONAL BANCORPORATION, INC","cik":"0000750574","sic_code":"6022","sic_industry":"State Commercial Banks","sic_major_group":"Finance, Insurance, Real Estate","buy_value_usd":8363.265,"market_cap_usd":83795905.61957932,"ratio_to_mcap":9.980517470588542e-05,"num_insiders":1,"top_insider":{"name":"Conn Walton T Jr.","title":null},"transactions":[{"date":"2026-04-30","insider_name":"Conn Walton T Jr.","insider_title":null,"shares":200.0,"price":23.895,"value_usd":4779.0},{"date":"2026-04-30","insider_name":"Conn Walton T Jr.","insider_title":null,"shares":150.0,"price":23.8951,"value_usd":3584.265}]},{"rank":8,"ticker":"SBMT","company_name":"SILVER BOW MINING CORP.","cik":"0002067674","sic_code":"1040","sic_industry":"Gold Mining","sic_major_group":"Mining","buy_value_usd":5375.0,"market_cap_usd":0,"ratio_to_mcap":0,"num_insiders":1,"top_insider":{"name":"Black Wade Newton","title":"Chief Financial Officer"},"transactions":[{"date":"2026-04-30","insider_name":"Black Wade Newton","insider_title":"Chief Financial Officer","shares":500.0,"price":10.75,"value_usd":5375.0}]},{"rank":9,"ticker":"ATLO","company_name":"AMES NATIONAL CORP","cik":"0001132651","sic_code":"6021","sic_industry":"National Commercial Banks","sic_major_group":"Finance, Insurance, Real Estate","buy_value_usd":2358.72,"market_cap_usd":249596462.30300903,"ratio_to_mcap":9.450133941147467e-06,"num_insiders":1,"top_insider":{"name":"Cassabaum Michelle R","title":null},"transactions":[{"date":"2026-04-30","insider_name":"Cassabaum Michelle R","insider_title":null,"shares":84.0,"price":28.08,"value_usd":2358.72}]}]}